terrace/__init__.py
terrace/data/__init__.py
terrace/data/context.py
terrace/data/field.py
terrace/data/providers/__init__.py
terrace/data/providers/csv.py
terrace/data/providers/provider.py
terrace/helpers/__init__.py
terrace/helpers/ta.py
terrace/strategy/__init__.py
terrace/strategy/strategy.py
terrace_engine-0.0.1.dist-info/LICENSE
terrace_engine-0.0.1.dist-info/METADATA
terrace_engine-0.0.1.dist-info/WHEEL
terrace_engine-0.0.1.dist-info/top_level.txt
terrace_engine-0.0.1.dist-info/RECORD
