Metadata-Version: 2.1
Name: terrace-engine
Version: 0.0.1
Summary: an open source algorithmic trading engine optimized for a great developer experience
Home-page: https://github.com/carterjfulcher/terrace
Author: carterjfulcher
Author-email: Carter Fulcher <carter@fulcheranalytics.io>
License: MIT
Project-URL: Homepage, https://github.com/carterfulcher/terrace
Project-URL: Bug Tracker, https://github.com/carterfulcher/terrace/issues
Platform: any
Classifier: Programming Language :: Python :: 3
Classifier: License :: OSI Approved :: MIT License
Classifier: Operating System :: OS Independent
Requires-Python: >=3.9
License-File: LICENSE
